[{"titleJP":"エスタブライフ グレイトエスケープ","titleCN":"Estab Life:Great Escape","begin":"2022-04-06T15:35:00.000Z","bangumiId":366253,"anidbId":16794},{"titleJP":"ラブライブ！虹ヶ咲学園スクールアイドル同好会(第2期)","titleCN":"Love Live! 虹咲学园校园偶像同好会 第二季","begin":"2022-04-02T13:00:00.000Z","bangumiId":335579,"anidbId":16310},{"titleJP":"まちカドまぞく 2丁目","titleCN":"街角魔族 2丁目","begin":"2022-04-07T16:28:00.000Z","bangumiId":313852,"anidbId":15702},{"titleJP":"魔法使い黎明期","titleCN":"魔法使黎明期","begin":"2022-04-07T16:58:00.000Z","bangumiId":334319,"anidbId":16280},{"titleJP":"可愛いだけじゃない式守さん","titleCN":"我家女友可不止可爱呢","begin":"2022-04-09T17:00:00.000Z","bangumiId":324295,"anidbId":15964},{"titleJP":"阿波連さんははかれない","titleCN":"测不准的阿波连同学","begin":"2022-04-01T17:25:00.000Z","bangumiId":343656,"anidbId":16505},{"titleJP":"八十亀ちゃんかんさつにっき 4さつめ","titleCN":"八十龟酱观察日记 第四册","begin":"2022-04-09T11:54:00.000Z","bangumiId":359527,"anidbId":17003},{"titleJP":"処刑少女の生きる道","titleCN":"处刑少女的生存之道","begin":"2022-04-01T15:30:00.000Z","bangumiId":326871,"anidbId":16031},{"titleJP":"勇者、辞めます","titleCN":"勇者辞职不干了","begin":"2022-04-05T13:30:00.000Z","bangumiId":353657,"anidbId":16917},{"titleJP":"このヒーラー、めんどくさい","titleCN":"这个医师超麻烦","begin":"2022-04-10T12:00:00.000Z","bangumiId":333176,"anidbId":16249},{"titleJP":"乙女ゲー世界はモブに厳しい世界です","titleCN":"乙女游戏世界对路人角色很不友好","begin":"2022-04-03T13:00:00.000Z","bangumiId":359980,"anidbId":17005},{"titleJP":"であいもん","titleCN":"相合之物","begin":"2022-04-06T14:30:00.000Z","bangumiId":333664,"anidbId":16270},{"titleJP":"本好きの下剋上 司書になるためには手段を選んでいられません(第3期)","titleCN":"小书痴的下克上～为了成为图书管理员而不择手段～ 第3部","begin":"2022-04-14T14:00:00.000Z","bangumiId":310263,"anidbId":15634},{"titleJP":"骸骨騎士様、只今異世界へお出掛け中","titleCN":"骸骨骑士大人异世界冒险中","begin":"2022-04-07T14:30:00.000Z","bangumiId":333448,"anidbId":16262},{"titleJP":"古見さんは、コミュ症です。(第2期)","titleCN":"古见同学有交流障碍症 第二季","begin":"2022-04-06T15:00:00.000Z","bangumiId":363242,"anidbId":16300},{"titleJP":"社畜さんは幼女幽霊に癒されたい。","titleCN":"社畜小姐想被幽灵幼女治愈。","begin":"2022-04-07T12:00:00.000Z","bangumiId":338653,"anidbId":16376},{"titleJP":"シャドウバースF","titleCN":"影之诗F","begin":"2022-04-02T01:00:00.000Z","bangumiId":351943,"anidbId":16855},{"titleJP":"ブラック★★ロックシューター DAWN FALL","titleCN":"黑岩射手 DAWN FALL","begin":"2022-04-03T14:00:00.000Z","bangumiId":349465,"anidbId":16705},{"titleJP":"ヒロインたるもの! ~嫌われヒロインと内緒のお仕事~","titleCN":"身为女主角 讨厌的女主角与秘密的工作","begin":"2022-04-07T13:30:00.000Z","bangumiId":347140,"anidbId":16564},{"titleJP":"恋は世界征服のあとで","titleCN":"恋爱要在世界征服后","begin":"2022-04-08T12:30:00.000Z","bangumiId":332446,"anidbId":16183},{"titleJP":"ラブオールプレー","titleCN":"LOVE ALL PLAY","begin":"2022-04-02T08:30:00.000Z","bangumiId":345705,"anidbId":16527},{"titleJP":"デュエル・マスターズ キングMAX","titleCN":"DUEL MASTERS KINGMAX","begin":"2022-04-02T23:30:00.000Z","bangumiId":-1,"anidbId":17195},{"titleJP":"キャップ革命 ボトルマンDX","titleCN":"帽子革命瓶子人 DX","begin":"2022-04-03T00:30:00.000Z","bangumiId":372925,"anidbId":17232},{"titleJP":"インセクトランド","titleCN":"昆虫乐园","begin":"2022-04-03T23:45:00.000Z","bangumiId":371892,"anidbId":16495},{"titleJP":"もっと！まじめにふまじめ かいけつゾロリ(第3シリーズ)","titleCN":"更多！正经又不正经 怪侠佐罗利","begin":"2022-04-06T10:00:00.000Z","bangumiId":353906,"anidbId":14986},{"titleJP":"群青のファンファーレ","titleCN":"群青的号角","begin":"2022-04-02T14:30:00.000Z","bangumiId":347953,"anidbId":16563},{"titleJP":"RPG不動産","titleCN":"RPG不动产","begin":"2022-04-06T12:30:00.000Z","bangumiId":329285,"anidbId":16078},{"titleJP":"デート・ア・ライブⅣ","titleCN":"约会大作战 第四季","begin":"2022-04-08T13:00:00.000Z","bangumiId":302128,"anidbId":15106},{"titleJP":"SPY×FAMILY","titleTranslate":"间谍过家家","begin":"2022-04-09T14:00:00.000Z","bangumiId":329906,"anidbId":16947},{"titleJP":"遊☆戯☆王ゴーラッシュ!!","titleCN":"游戏王 Go Rush！！","begin":"2022-04-02T22:30:00.000Z","bangumiId":362997,"anidbId":17062},{"titleJP":"理系が恋に落ちたので証明してみた。r=1-sinθ","titleCN":"理科生坠入情网故尝试证明[r=1-sinθ ]❤","begin":"2022-04-01T16:30:00.000Z","bangumiId":317042,"anidbId":15788},{"titleJP":"アオアシ","titleCN":"青之芦苇","begin":"2022-04-09T09:25:00.000Z","bangumiId":337459,"anidbId":16948},{"titleJP":"トモダチゲーム","titleCN":"朋友游戏","begin":"2022-04-05T16:29:00.000Z","bangumiId":355072,"anidbId":16948},{"titleJP":"ヒーラー・ガール","titleCN":"歌愈少女","begin":"2022-04-04T14:00:00.000Z","bangumiId":334498,"anidbId":16286},{"titleJP":"サマータイムレンダ","titleCN":"夏日重现","begin":"2022-04-14T15:00:00.000Z","bangumiId":326895,"anidbId":16033},{"titleJP":"BIRDIE WING -Golf Girls' Story-","titleCN":"小鸟之翼","begin":"2022-04-05T15:00:00.000Z","bangumiId":354682,"anidbId":16940},{"titleJP":"くノ一ツバキの胸の内","titleCN":"女忍者椿的心事","begin":"2022-04-09T15:00:00.000Z","bangumiId":351973,"anidbId":16966},{"titleJP":"キングダム(第4シリーズ)","titleCN":"王者天下 第四季","begin":"2022-04-09T15:00:00.000Z","bangumiId":353266,"anidbId":16912},{"titleJP":"かぐや様は告らせたい-ウルトラロマンティック-","titleCN":"辉夜大小姐想让我告白-Ultra Romantic-","begin":"2022-04-08T15:00:00.000Z","bangumiId":317613,"anidbId":15806},{"titleJP":"盾の勇者の成り上がり Season 2","titleCN":"盾之勇者成名录 第二季","begin":"2022-04-06T13:00:00.000Z","bangumiId":289906,"anidbId":15806},{"titleJP":"ダンス・ダンス・ダンスール","titleCN":"舞动不止","begin":"2022-04-08T16:25:00.000Z","bangumiId":332585,"anidbId":16196},{"titleJP":"ビルディバイド -#FFFFFF-","titleCN":"Build Divide -#FFFFFF-","begin":"2022-04-02T15:30:00.000Z","bangumiId":333624,"anidbId":16266},{"titleJP":"史上最強の大魔王、村人Aに転生する","titleCN":"史上最强的大魔王转生为村人A","begin":"2022-04-06T12:00:00.000Z","bangumiId":330055,"anidbId":16100},{"titleJP":"3秒後、野獣。～合コンで隅にいた彼は肉食でした","titleCN":"3秒后，野兽。～坐在联谊会角落的他是个肉食系","begin":"2022-04-03T16:00:00.000Z","bangumiId":354246,"anidbId":16934},{"titleJP":"じゃんたま PONG★","titleCN":"雀魂 PONG☆","begin":"2022-04-01T16:52:00.000Z","bangumiId":365297,"anidbId":17127},{"titleJP":"カッコウの許嫁","titleCN":"杜鹃的婚约","begin":"2022-04-23T16:30:00.000Z","bangumiId":327606,"anidbId":16188},{"titleJP":"境界戦機 第二部","titleCN":"境界战机 第二部","begin":"2022-04-11T16:00:00.000Z","bangumiId":363959,"anidbId":17091},{"titleJP":"かぎなど シーズン2","titleCN":"键等 第二季","begin":"2022-04-12T16:00:00.000Z","bangumiId":363880,"anidbId":17089},{"titleJP":"名探偵コナン ゼロの日常","titleCN":"名侦探柯南 零的日常","begin":"2022-04-04T16:20:00.000Z","bangumiId":351714,"anidbId":16842},{"titleJP":"ちいかわ","titleCN":"小可爱","begin":"","bangumiId":354700,"anidbId":16943},{"titleJP":"おにぱん!","titleCN":"鬼裤衩","begin":"2022-04-15T03:00:00.000Z","bangumiId":367727,"anidbId":17178},{"titleJP":"パリピ孔明","titleCN":"派对浪客诸葛孔明","begin":"2022-04-05T14:00:00.000Z","bangumiId":356756,"anidbId":16970},{"titleJP":"マギアレコード 魔法少女まどか☆マギカ外伝 Final Season -浅き夢の暁-","titleCN":"魔法纪录 魔法少女小圆外传 Final SEASON -浅梦的黎明-","begin":"2022-04-03T13:00:00.000Z","bangumiId":339998,"anidbId":16404}]